[{"h":"prove/2013-asoe-physics-exam__q12","l":"ASOE 2013 · Problema 12","s":"Question 12","f":"au","c":"Australia","lv":"nazionale","y":"2013"},{"h":"prove/2014-asoe-physics-exam__q13","l":"ASOE 2014 · Problema 13","s":"Question 13","f":"au","c":"Australia","lv":"nazionale","y":"2014"},{"h":"prove/anainlab_2023__q01","l":"Anacleto 2023 Nazionale Sperimentale · Problema 1","s":"Esperienza di laboratorio di *Anacleto in Lab 2023* (guida per i docen","f":"it","c":"Italy","lv":"Nazionale","y":"2023"},{"h":"prove/cuadernillo_2005__q01","l":"Argent 2005 · Problema 1","s":"Olimpíada Argentina de Física","f":"ar","c":"Argentina","lv":"Locale","y":"2005"},{"h":"prove/cuadernillo_2014__q05","l":"Argent 2014 · Problema 5","s":"Problema 2","f":"ar","c":"Argentina","lv":"Locale","y":"2014"},{"h":"prove/prueba_2014__q05","l":"Argent 2014 · Problema 5","s":"Problema 2","f":"ar","c":"Argentina","lv":"nazionale","y":"2014"},{"h":"prove/cuadernillo_2017__q01","l":"Argent 2017 · Problema 1","s":"Problema 1","f":"ar","c":"Argentina","lv":"Locale","y":"2017"},{"h":"prove/cuadernillo_2017__q04","l":"Argent 2017 · Problema 4","s":"Problema 1","f":"ar","c":"Argentina","lv":"Locale","y":"2017"},{"h":"prove/prueba_2017__q01","l":"Argent 2017 · Problema 1","s":"Problema 1","f":"ar","c":"Argentina","lv":"nazionale","y":"2017"},{"h":"prove/prueba_2017__q04","l":"Argent 2017 · Problema 4","s":"Problema 1","f":"ar","c":"Argentina","lv":"nazionale","y":"2017"},{"h":"prove/juegos_2018_final_1__q02","l":"Argent 2018 Locale Quiz · Problema 2","s":"*(Juegos de OAF 2018 — Prueba 1. Quiz a risposta multipla.)*","f":"ar","c":"Argentina","lv":"Locale","y":"2018"},{"h":"prove/cuadernillo_2018__q10","l":"Argent 2018 Locale · Problema 10","s":"PT4. Colegio Juan Humberto Morán. Eduardo Castex, La Pampa.","f":"ar","c":"Argentina","lv":"Locale","y":"2018"},{"h":"prove/cuadernillo_2018__q180","l":"Argent 2018 Locale · Problema 180","s":"PT174. Escuela ORT - Sede Almagro. Ciudad Autónoma de Buenos","f":"ar","c":"Argentina","lv":"Locale","y":"2018"},{"h":"prove/cuadernillo_2018__q230","l":"Argent 2018 Locale · Problema 230","s":"PE51. Instituto Eduardo L. Holmberg. Quilmes, Buenos Aires.","f":"ar","c":"Argentina","lv":"Locale","y":"2018"},{"h":"prove/cuadernillo_2018__q37","l":"Argent 2018 Locale · Problema 37","s":"PT31. Escuela Técnica ORT N° 2. Ciudad Autónoma de Buenos Ai","f":"ar","c":"Argentina","lv":"Locale","y":"2018"},{"h":"prove/cuadernillo_2018__q44","l":"Argent 2018 Locale · Problema 44","s":"PT38. Escuela Municipal Paula Albarracín de Sarmiento. Olivo","f":"ar","c":"Argentina","lv":"Locale","y":"2018"},{"h":"prove/2020_2da_prueba_preparatoria__q02","l":"Argent 2020 · Problema 2","s":"Problema 2","f":"ar","c":"Argentina","lv":"allenamento","y":"2020"},{"h":"prove/cuadernillo_2020__q08","l":"Argent 2020 · Problema 8","s":"Problema 2","f":"ar","c":"Argentina","lv":"Locale","y":"2020"},{"h":"prove/2021-nbpho_2021_eng__q02","l":"BPhO 2021 · Problema 2","s":"2. GAs AND FLUıD FLOWs (10 points) — Jaan","f":"","c":"Nordic-Baltic","lv":"internazionale","y":"2021"},{"h":"prove/teon3f3__q05","l":"Brasil 2006 · Problema 5","s":"Questão 5 – Um recipiente contendo água possui uma pequena abertura de","f":"br","c":"Brazil","lv":"nazionale","y":"2006"},{"h":"prove/prova-2fase_nivel3a_2016__q02","l":"Brasil 2016 · Problema 2","s":"Questão 2 – A usina hidrelétrica ocupa posição de destaque no sistema","f":"br","c":"Brazil","lv":"nazionale","y":"2016"},{"h":"prove/prova-2fase_nivel3a_2016_2#problema-2","l":"Brasil 2016 · Problema 2","s":"Questão 2 – A usina hidrelétrica ocupa posição de destaque no sistema","f":"br","c":"Brazil","lv":"nazionale","y":"2016"},{"h":"prove/teon3f3_2#problema-5","l":"Brasil 2016 · Problema 5","s":"Questão 5 – Um recipiente contendo água possui uma pequena abertura de","f":"br","c":"Brazil","lv":"nazionale","y":"2016"},{"h":"prove/nivel1_2#problema-7","l":"Brasil 2017 · Problema 7","s":"Questão 7. Uma pessoa observa que demora, em média, 20 horas para ench","f":"br","c":"Brazil","lv":"nazionale","y":"2017"},{"h":"prove/provaniel2fase1final2017b__q24","l":"Brasil 2017 · Problema 24","s":"24. Cuidado com o que você come Professor Physicson, evite gorduras sa","f":"br","c":"Brazil","lv":"qualifica","y":"2017"},{"h":"prove/provaniel2fase1final2017b_2#problema-24","l":"Brasil 2017 · Problema 24","s":"24. Cuidado com o que você come Professor Physicson, evite gorduras sa","f":"br","c":"Brazil","lv":"qualifica","y":"2017"},{"h":"prove/provanivel3fase1final2017b__q14","l":"Brasil 2017 · Problema 14","s":"14. Cuidado com o que você come Professor Physicson, evite gorduras sa","f":"br","c":"Brazil","lv":"qualifica","y":"2017"},{"h":"prove/provanivel3fase1final2017b_2#problema-14","l":"Brasil 2017 · Problema 14","s":"14. Cuidado com o que você come Professor Physicson, evite gorduras sa","f":"br","c":"Brazil","lv":"qualifica","y":"2017"},{"h":"prove/fase2_n2__q11","l":"Brasil 2024 · Problema 11","s":"Questão 11. Um proprietário rural cava uma cisterna em sua residência","f":"br","c":"Brazil","lv":"nazionale","y":"2024"},{"h":"prove/fase2_n3__q08","l":"Brasil 2024 · Problema 8","s":"Questão 8. Um proprietário rural cava uma cisterna em sua residência e","f":"br","c":"Brazil","lv":"nazionale","y":"2024"},{"h":"prove/fase1_n2_2#problema-16","l":"Brasil 2025 · Problema 16","s":"Questão 16.","f":"br","c":"Brazil","lv":"qualifica","y":"2025"},{"h":"prove/fase1_n3_2#problema-10","l":"Brasil 2025 · Problema 10","s":"Questão 10.","f":"br","c":"Brazil","lv":"qualifica","y":"2025"},{"h":"prove/2024_fma__q21","l":"F=ma 2024 · Problema 21","s":"21. A syringe is filled with water of density $\\rho$ and negligible vi","f":"us","c":"United States","lv":"qualifica","y":"2024"},{"h":"prove/2025_fma__q21","l":"F=ma 2025 · Problema 21","s":"21. What is the difference in the speed of water between the two pipes","f":"us","c":"United States","lv":"qualifica","y":"2025"},{"h":"prove/2025_fma__q22","l":"F=ma 2025 · Problema 22","s":"22. To measure this difference, two graduated cylinders are connected","f":"us","c":"United States","lv":"qualifica","y":"2025"},{"h":"prove/all_sanvito_2025t__q12","l":"GaS 2025 Allenamento Quiz · Problema 12","s":"In quel di San Vito","f":"it","c":"Italy","lv":"allenamento","y":"2025"},{"h":"prove/all_sanvito_2025t__q07","l":"GaS 2025 Allenamento Quiz · Problema 7","s":"Fontana di Erone","f":"it","c":"Italy","lv":"allenamento","y":"2025"},{"h":"prove/allenamento_righiseconda_2026t__q12","l":"GaS 2026 Locale Squadre · Problema 12","s":"Il tubo di Venturi","f":"it","c":"Italy","lv":"locale","y":"2026"},{"h":"prove/inpho2018-question#problema-16","l":"INPhO 2018 · Problema 16","s":"7.","f":"in","c":"India","lv":"nazionale","y":"2018"},{"h":"prove/inbo2017-question#problema-3","l":"India 2017 · Problema 3","s":"3. (1 point) A tuberculosis patient died within a few minutes of secon","f":"in","c":"India","lv":"nazionale","y":"2017"},{"h":"prove/ioqp2022-partii-questions-en#problema-9","l":"India 2022 · Problema 9","s":"3. Consider an air filled spherical balloon comprised of elastic mater","f":"in","c":"India","lv":"nazionale","y":"2022"},{"h":"prove/inbo2024-question-en#problema-41","l":"India 2024 '' · Problema 41","s":"(Plant Sciences — 2 points)","f":"in","c":"India","lv":"nazionale","y":"2024"},{"h":"prove/obf2006_3fase_1-and-2_serie_prova__q17","l":"OBF 2006 · Problema 17","s":"Questão 17) A mangueira de regar jardins representada lança um jato de","f":"br","c":"Brazil","lv":"qualifica","y":"2006"},{"h":"prove/obf2011_f3_3o__q03","l":"OBF 2011 · Problema 3","s":"Questão 3 - Um cilindro de paredes condutoras térmicas possui um embol","f":"br","c":"Brazil","lv":"nazionale","y":"2011"},{"h":"prove/obf-2018-f1-n3__q20","l":"OBF 2018 '' · Problema 20","s":"A arteriosclerose refere-se ao estreitamento (esclerose) das arteríola","f":"br","c":"Brazil","lv":"nazionale","y":"2018"},{"h":"prove/obf-2021-f23-n1__q04","l":"OBF 2021 · Problema 4","s":"Questão 4. A ponte fluvial de Magdeburgo, na Alemanha, inaulgurada em","f":"br","c":"Brazil","lv":"nazionale","y":"2021"},{"h":"prove/obf-2021-f23-n2__q08","l":"OBF 2021 · Problema 8","s":"Questão 8. A ponte fluvial de Magdeburgo, na Alemanha, inaulgurada em","f":"br","c":"Brazil","lv":"nazionale","y":"2021"},{"h":"prove/obf-2022-f2-n3__q08","l":"OBF 2022 · Problema 8","s":"Questão 8. A","f":"br","c":"Brazil","lv":"nazionale","y":"2022"},{"h":"prove/obf-2022-f3-n2__q06","l":"OBF 2022 · Problema 6","s":"Questão 6.","f":"br","c":"Brazil","lv":"nazionale","y":"2022"},{"h":"prove/obf-2022-f3-n2__q09","l":"OBF 2022 · Problema 9","s":"Questão 9.","f":"br","c":"Brazil","lv":"nazionale","y":"2022"},{"h":"prove/obf-2022-f3-n3__q05","l":"OBF 2022 · Problema 5","s":"Questão 5.","f":"br","c":"Brazil","lv":"nazionale","y":"2022"},{"h":"prove/obf-2023-f1-n3__q16","l":"OBF 2023 · Problema 16","s":"Questão 16.","f":"br","c":"Brazil","lv":"nazionale","y":"2023"},{"h":"prove/obf-2023-f2-njr__q08","l":"OBF 2023 · Problema 8","s":"Questão 8.","f":"br","c":"Brazil","lv":"nazionale","y":"2023"},{"h":"prove/naz00th__q01","l":"OII 2000 Nazionale Teorica · Problema 1","s":"Tre in uno!","f":"it","c":"Italy","lv":"nazionale","y":"2000"},{"h":"prove/itaspefr__q01","l":"OII 2004 'IPhO sperimentale' · Problema 1","s":"### La Scatola Nera Meccanica","f":"","c":"International","lv":"internazionale","y":"2004"},{"h":"prove/2lv05t__q09","l":"OII 2005 2° Livello Teorica · Problema 9","s":"Da un rubinetto, un getto d'acqua scende verticalmente con una sezione","f":"it","c":"Italy","lv":"2 livello","y":"2005"},{"h":"prove/1lv06t__q11","l":"OII 2006 1° Livello · Quesito 11","s":"Un getto d'acqua di densità $\\rho$, area della sezione trasversale $A$","f":"it","c":"Italy","lv":"1 livello","y":"2006"},{"h":"prove/version-5-ipho2013_t3_italiano__q01","l":"OII 2013 '' · Problema 1","s":"**(3.1)** Utilizzando le ipotesi 1–3 e la conservazione della massa, r","f":"","c":"International","lv":"internazionale","y":"2013"},{"h":"prove/version-5-ipho2013_t3_italiano__q04","l":"OII 2013 '' · Problema 4","s":"**(3.4)** Scrivi un'espressione per la dipendenza da $z$ della compone","f":"","c":"International","lv":"internazionale","y":"2013"},{"h":"prove/version-5-ipho2013_t3_italiano__q05","l":"OII 2013 '' · Problema 5","s":"**(3.5 – 3.9)** Questa sezione comprende i sottoproblemi relativi alle","f":"","c":"International","lv":"internazionale","y":"2013"},{"h":"prove/2liv24t__q10","l":"OII 2024 2° Livello · Problema 10","s":"q10","f":"it","c":"Italy","lv":"2 livello","y":"2024"},{"h":"prove/2liv25q__q10","l":"OII 2025 2° Livello · Problema 10","s":"q10","f":"it","c":"Italy","lv":"2 livello","y":"2025"},{"h":"prove/exam-theory-a3-italian__q01","l":"OII na Teorica · Problema 1","s":"Theory","f":"","c":"International","lv":"internazionale","y":""},{"h":"prove/ipho-37.th3_final_ita__q12","l":"OII na Teorica · Problema 12","s":"**Vasi capillari** Consideriamo il sangue come un fluido vis","f":"","c":"International","lv":"internazionale","y":""},{"h":"prove/ipho-37.th3_final_ita__q13","l":"OII na Teorica · Problema 13","s":"**Vasi capillari (segue)** Stesse condizioni del problema 3.","f":"","c":"International","lv":"internazionale","y":""},{"h":"prove/exam-theory-q3__q01","l":"OII na Teorica · Problema 1","s":"1.","f":"","c":"International","lv":"internazionale","y":""},{"h":"prove/ipho-37.th3_final_ita__q01","l":"OII na Teorica · Problema 1","s":"a Teorico n. 3","f":"","c":"International","lv":"internazionale","y":""},{"h":"prove/teorico-3-hanoi__q05","l":"OII na Teorica · Problema 5","s":"5. Stima dell’inquinamento da monossido di carbonio (CO) da","f":"","c":"International","lv":"internazionale","y":""},{"h":"prove/th2ita__q01","l":"OII na Teorica · Problema 1","s":"Introduzione","f":"","c":"International","lv":"internazionale","y":""},{"h":"prove/2022_phods_mock_f_ma___q03","l":"Russia 2022 · Problema 3","s":"3. A sprinkler can be modelled as a hemisphere with N evenly divided h","f":"us","c":"United States","lv":"nazionale","y":"2022"},{"h":"prove/solswilliam__q03","l":"Russia na · Problema 3","s":"Problem 3","f":"ru","c":"Russia","lv":"nazionale","y":""},{"h":"prove/p2-oef-2008__q06","l":"Spagna 2008 · Problema 6","s":"6)","f":"es","c":"Spain","lv":"nazionale","y":"2008"},{"h":"prove/2015-primera_prueba_2015__q02","l":"Spagna 2015 · Problema 2","s":"P2 Intercambios de calor.","f":"es","c":"Spain","lv":"locale","y":"2015"},{"h":"prove/2022__q04","l":"Spagna 2022 · Problema 4","s":"EJERCICIO 4.","f":"es","c":"Spain","lv":"locale","y":"2022"},{"h":"prove/p1_la_dana_de_octubre__q01","l":"Spagna 2025 · Problema 1","s":"P1. La DANA de octubre","f":"es","c":"Spain","lv":"nazionale","y":"2025"},{"h":"prove/p1_la_dana_de_octubre__q05","l":"Spagna 2025 · Problema 05","s":"**P1. La DANA de octubre** — Parte e) Una corriente de agua","f":"es","c":"Spain","lv":"nazionale","y":"2025"},{"h":"prove/p1_la_dana_de_octubre__q08","l":"Spagna 2025 · Problema 08","s":"**P1. La DANA de octubre** — Parte h) Otro sensor de ultraso","f":"es","c":"Spain","lv":"nazionale","y":"2025"},{"h":"prove/2026-prueba_2026__q05","l":"Spagna 2026 · Problema 5","s":"Ejercicio 5 (1 punto). Supongamos que la abertura tiene una peque ̃na","f":"es","c":"Spain","lv":"locale","y":"2026"},{"h":"prove/2026-prueba_2026__q07","l":"Spagna 2026 · Problema 7","s":"Ejercicio 7 (2 puntos). Consideremos una clepsidra con simetr ́ıa de r","f":"es","c":"Spain","lv":"locale","y":"2026"},{"h":"prove/2026-soluciones_2026#problema-12","l":"Spagna 2026 · Problema 12","s":"Ejercicio 5 (1 punto)","f":"es","c":"Spain","lv":"locale","y":"2026"},{"h":"prove/2026-soluciones_2026#problema-5","l":"Spagna 2026 · Problema 5","s":"Ejercicio 5 (1 punto). Supongamos que la abertura tiene una peque ̃na","f":"es","c":"Spain","lv":"locale","y":"2026"},{"h":"prove/2026-soluciones_2026#problema-7","l":"Spagna 2026 · Problema 7","s":"Ejercicio 7 (2 puntos). Consideremos una clepsidra con simetr ́ıa de r","f":"es","c":"Spain","lv":"locale","y":"2026"},{"h":"prove/2011jan_r2__q01","l":"UK 2011 · Problema 1","s":"Q1","f":"gb","c":"United Kingdom","lv":"nazionale","y":"2011"},{"h":"prove/2011nov_r1_s1__q12","l":"UK 2011 · Problema 12","s":"A rescue helicopter of mass 810 kg, supports itself in a sta","f":"gb","c":"United Kingdom","lv":"qualifica","y":"2011"},{"h":"prove/2023nov_r1_s2","l":"UK 2023 · Problema 1","s":"10th November 2023","f":"gb","c":"United Kingdom","lv":"qualifica","y":"2023"},{"h":"prove/2023nov_r1_s2__q02","l":"UK 2023 · Problema 02","s":"**Question 2** — This question is about wind turbines. a) As","f":"gb","c":"United Kingdom","lv":"qualifica","y":"2023"},{"h":"prove/2012-exam1-2012-unlocked__q19","l":"USA 2012 · Problema 19","s":"19. A 1,500 Watt motor is used to pump water a vertical height of 2.0","f":"us","c":"United States","lv":"qualifica","y":"2012"},{"h":"prove/2022_theory_tst__q05","l":"USA 2022 · Problema 5","s":"5. An empty cylindrical glass of cross-sectional area A is resting on","f":"us","c":"United States","lv":"nazionale","y":"2022"},{"h":"prove/1liv23t__q35","l":"OII 2023 1° Livello Quiz · Quesito 35","s":"Un liquido scorre in regime stazionario in un condotto con u","f":"it","c":"Italy","lv":"1 livello","y":"2023"},{"h":"prove/1liv23t-fasc__q35","l":"OII 2023 1° Livello · Quesito 35","s":"Un liquido scorre, in regime stazionario, in un condotto che","f":"it","c":"Italy","lv":"1 livello","y":"2023"},{"h":"prove/2023t__q35","l":"OII 2023 1° Livello · Quesito 35","s":"Un liquido scorre, in regime stazionario, in un condotto che","f":"it","c":"Italy","lv":"1 livello","y":"2023"},{"h":"prove/1lv03t__q04","l":"OII 2003 1° Livello Quiz · Quesito 4","s":"Dell'acqua, che scorre adagio in un largo condotto, attraver","f":"it","c":"Italy","lv":"1 livello","y":"2003"},{"h":"prove/1liv11t__q26","l":"OII 2011 1° Livello · Quesito 26","s":"Un fluido omogeneo e non comprimibile scorre in regime stazi","f":"it","c":"Italy","lv":"1 livello","y":"2011"},{"h":"prove/nsep_2023_question__q10","l":"NSEP 2023 · Problema 10","s":"Water flows at 1.2 m/s through a hose of diameter 1.59 cm. T","f":"in","c":"India","lv":"qualifica","y":"2023"},{"h":"prove/nsep_2024_question__q24","l":"NSEP 2024 · Problema 24","s":"A cylindrical tank with base area $A = 0.05$ m$^2$ is filled","f":"in","c":"India","lv":"qualifica","y":"2024"},{"h":"prove/nsep_2025_question__q16","l":"NSEP 2025 · Problema 16","s":"A large tank, open at the top, has two small holes in the ve","f":"in","c":"India","lv":"qualifica","y":"2025"},{"h":"prove/injso2011-q__q50","l":"INJSO 2011 · Problema 50","s":"In the figure shown below, there are two tanks I and II with","f":"in","c":"India","lv":"nazionale","y":"2011"},{"h":"prove/2005-e_s_2005_e__q04","l":"Nordic 2005 · Problema 04","s":"**Water pump** (10 points) Consider the following constructi","f":"","c":"Nordic-Baltic","lv":"internazionale","y":"2005"},{"h":"prove/2010_fma__q23","l":"F=ma 2010 · Problema 23","s":"Two streams of water flow through the U-shaped tubes shown.","f":"us","c":"United States","lv":"qualifica","y":"2010"},{"h":"prove/2017nov_r1_s1__q05","l":"UK 2017 · Problema 05","s":"A helicopter of total mass 1000 kg is able to remain in a st","f":"gb","c":"United Kingdom","lv":"qualifica","y":"2017"},{"h":"prove/2018nov_r1_s2__q04","l":"UK 2018 · Problema 04","s":"**Question 4.** **(a)** Show that the pressure at depth $h$","f":"gb","c":"United Kingdom","lv":"qualifica","y":"2018"},{"h":"prove/2020_usapho__q04","l":"USAPhO 2020 · Problema 04","s":"**Question B1 — String Cheese** a. When a faucet is turned o","f":"us","c":"United States","lv":"nazionale","y":"2020"},{"h":"prove/apho_2009_theory__q03","l":"APhO 2009 · Problema 03","s":"**The Leidenfrost Phenomenon** The purpose is to estimate th","f":"","c":"Asia","lv":"Internazionale","y":"2009"},{"h":"prove/apho_2010_theory__q03","l":"APhO 2010 · Problema 03","s":"**Theoretical Question 3 — Electron and Gas Bubbles in Liqui","f":"","c":"Asia","lv":"Internazionale","y":"2010"},{"h":"prove/apho_2017_theory__q01","l":"APhO 2017 · Problema 01","s":"### Vortices in superfluid #### Introduction Superfluidity i","f":"","c":"Asia","lv":"Internazionale","y":"2017"},{"h":"prove/apho_2019_theory__q02","l":"APhO 2019 · Problema 02","s":"**X-ray jets from active galactic nuclei** ### Introduction","f":"","c":"Asia","lv":"Internazionale","y":"2019"},{"h":"prove/apho_2021_theory__q01","l":"APhO 2021 · Problema 01","s":"### Water-Hammer Effect #### Introduction This problem studi","f":"","c":"Asia","lv":"Internazionale","y":"2021"},{"h":"prove/cuadernillo_1992__q66","l":"Argent 1992 Locale · Problema 66","s":"**62. Salta - Medidor con piezometros (Venturi)** 62. Salta.","f":"ar","c":"Argentina","lv":"Locale","y":"1992"},{"h":"prove/cuadernillo_1996__q177","l":"Argent 1996 Locale · Problema 177","s":"177. MAR DEL PLATA, BUENOS AIRES. AZUL Y VERDE. Se desea con","f":"ar","c":"Argentina","lv":"Locale","y":"1996"},{"h":"prove/cuadernillo_1996__q91","l":"Argent 1996 Locale · Problema 91","s":"91. MAR DEL PLATA, BUENOS AIRES. AZUL. ¿Dónde debería coloca","f":"ar","c":"Argentina","lv":"Locale","y":"1996"},{"h":"prove/cuadernillo_2005__q02","l":"Argent 2005 Locale · Problema 02","s":"**PT2 Caneria con objeto de madera (Bernoulli)** PT2. San Mi","f":"ar","c":"Argentina","lv":"Locale","y":"2005"},{"h":"prove/cuadernillo_2005__q140","l":"Argent 2005 Locale · Problema 140","s":"**PE24 Velocidad de salida de un grifo** PE24. San Miguel, T","f":"ar","c":"Argentina","lv":"Locale","y":"2005"},{"h":"prove/cuadernillo_2005__q153","l":"Argent 2005 Locale · Problema 153","s":"**PE37 Aceleracion de la gravedad con recursos hidrodinamico","f":"ar","c":"Argentina","lv":"Locale","y":"2005"},{"h":"prove/cuadernillo_2005__q29","l":"Argent 2005 Locale · Problema 29","s":"**PT29 Manguera con codo (chorro de agua)** PT29. Mar del Pl","f":"ar","c":"Argentina","lv":"Locale","y":"2005"},{"h":"prove/cuadernillo_2006__q168","l":"Argent 2006 Locale · Problema 168","s":"**Experimental: viscosidad especifica del agua (Poiseuille)*","f":"ar","c":"Argentina","lv":"Locale","y":"2006"},{"h":"prove/cuadernillo_2006__q73","l":"Argent 2006 Locale · Problema 73","s":"**Velocidad del agua del grifo, caudal** 73. Yerba Buena, Tu","f":"ar","c":"Argentina","lv":"Locale","y":"2006"},{"h":"prove/cuadernillo_2007__q118","l":"Argent 2007 Locale · Problema 118","s":"**Energia cinetica de la sangre en arteria** 118. San Miguel","f":"ar","c":"Argentina","lv":"Locale","y":"2007"},{"h":"prove/cuadernillo_2007__q36","l":"Argent 2007 Locale · Problema 36","s":"**Termotanque y calefon** 36. Ciudad de Buenos Aires. Azul.","f":"ar","c":"Argentina","lv":"Locale","y":"2007"},{"h":"prove/cuadernillo_2007__q84","l":"Argent 2007 Locale · Problema 84","s":"**Tuberia y teorema de Bernoulli** 84. Caleta Olivia. Santa","f":"ar","c":"Argentina","lv":"Locale","y":"2007"},{"h":"prove/cuadernillo_2008__q105","l":"Argent 2008 Locale · Problema 105","s":"**Todo por la economia** PT98. Ciudad de Mendoza. Azul. Todo","f":"ar","c":"Argentina","lv":"Locale","y":"2008"},{"h":"prove/cuadernillo_2008__q123","l":"Argent 2008 Locale · Problema 123","s":"**Flujo en canilla** PT116. Navarro, Buenos Aires. Verde. El","f":"ar","c":"Argentina","lv":"Locale","y":"2008"},{"h":"prove/cuadernillo_2008__q194","l":"Argent 2008 Locale · Problema 194","s":"**Leyes de la dinamica con chorro de agua** PE49. Ciudad de","f":"ar","c":"Argentina","lv":"Locale","y":"2008"},{"h":"prove/cuadernillo_2008__q63","l":"Argent 2008 Locale · Problema 63","s":"**Arteria renal** PT58. San Miguel de Tucumán. Azul. Por la","f":"ar","c":"Argentina","lv":"Locale","y":"2008"},{"h":"prove/cuadernillo_2008__q96","l":"Argent 2008 Locale · Problema 96","s":"**Caida de agua y generador** PT89. Ciudad de Santiago del E","f":"ar","c":"Argentina","lv":"Locale","y":"2008"},{"h":"prove/cuadernillo_2009__q122","l":"Argent 2009 Locale · Problema 122","s":"**Blood Flow Aorta to Capillaries** PT119. San Miguel de Tuc","f":"ar","c":"Argentina","lv":"Locale","y":"2009"},{"h":"prove/cuadernillo_2009__q125","l":"Argent 2009 Locale · Problema 125","s":"**Blood Speed Aorta and Capillaries** PT122. Navarro, Buenos","f":"ar","c":"Argentina","lv":"Locale","y":"2009"},{"h":"prove/cuadernillo_2009__q92","l":"Argent 2009 Locale · Problema 92","s":"**Oil Cooling via Water Radiator** PT89. Eduardo Castex, La","f":"ar","c":"Argentina","lv":"Locale","y":"2009"},{"h":"prove/cuadernillo_2010__q116","l":"Argent 2010 Locale · Problema 116","s":"PT113. Quilmes, Buenos Aires. Azul. El diagrama muestra el d","f":"ar","c":"Argentina","lv":"Locale","y":"2010"},{"h":"prove/cuadernillo_2010__q123","l":"Argent 2010 Locale · Problema 123","s":"PT120. San Miguel de Tucumán. Azul. Desde un depósito de gra","f":"ar","c":"Argentina","lv":"Locale","y":"2010"},{"h":"prove/cuadernillo_2010__q148","l":"Argent 2010 Locale · Problema 148","s":"**Sangre** PT145. Ciudad de Buenos Aires. Azul. Sangre El si","f":"ar","c":"Argentina","lv":"Locale","y":"2010"},{"h":"prove/cuadernillo_2010__q180","l":"Argent 2010 Locale · Problema 180","s":"**Teorema de Torricelli** PE32. San Miguel de Tucumán. Azul.","f":"ar","c":"Argentina","lv":"Locale","y":"2010"},{"h":"prove/cuadernillo_2010__q33","l":"Argent 2010 Locale · Problema 33","s":"PT30. Eduardo Castex, La Pampa. Azul. Un tanque de agua cilí","f":"ar","c":"Argentina","lv":"Locale","y":"2010"},{"h":"prove/cuadernillo_2010__q60","l":"Argent 2010 Locale · Problema 60","s":"PT57. San Ramón de la Nueva Orán, Salta. Azul. Un rayo laser","f":"ar","c":"Argentina","lv":"Locale","y":"2010"},{"h":"prove/cuadernillo_2011__q105","l":"Argent 2011 Locale · Problema 105","s":"**Tuberia y teorema de Bernoulli** PT96. Escuela Industrial","f":"ar","c":"Argentina","lv":"Locale","y":"2011"},{"h":"prove/cuadernillo_2011__q178","l":"Argent 2011 Locale · Problema 178","s":"**Velocidad de un chorro de agua** PE46. Escuela Industrial","f":"ar","c":"Argentina","lv":"Locale","y":"2011"},{"h":"prove/cuadernillo_2011__q68","l":"Argent 2011 Locale · Problema 68","s":"**Tanque de agua y caudal** PT62. Colegio María Auxiliadora","f":"ar","c":"Argentina","lv":"Locale","y":"2011"},{"h":"prove/cuadernillo_2012__q33","l":"Argent 2012 Locale · Problema 33","s":"PT30. Colegio Nacional de Buenos Aires Ciudad de Buenos Aire","f":"ar","c":"Argentina","lv":"Locale","y":"2012"},{"h":"prove/cuadernillo_2012__q71","l":"Argent 2012 Locale · Problema 71","s":"PT70. Escuela Superior de Comercio Carlos Pellegrini Ciudad","f":"ar","c":"Argentina","lv":"Locale","y":"2012"},{"h":"prove/cuadernillo_2013__q153","l":"Argent 2013 Locale · Problema 153","s":"**Gravedad con chorro de agua** PE45. Colegio del Sol San Mi","f":"ar","c":"Argentina","lv":"Locale","y":"2013"},{"h":"prove/cuadernillo_2014__q15","l":"Argent 2014 Locale · Problema 15","s":"**Tanque cilindrico con cano** PT9. Colegio Humberto Morán E","f":"ar","c":"Argentina","lv":"Locale","y":"2014"},{"h":"prove/cuadernillo_2015__q106","l":"Argent 2015 Locale · Problema 106","s":"PT90. Colegio Nacional de Monserrat Ciudad de Córdoba. Se ll","f":"ar","c":"Argentina","lv":"Locale","y":"2015"},{"h":"prove/cuadernillo_2015__q121","l":"Argent 2015 Locale · Problema 121","s":"PT105. Colegio San Ignacio Río Cuarto, Córdoba. El diagrama","f":"ar","c":"Argentina","lv":"Locale","y":"2015"},{"h":"prove/cuadernillo_2016__q107","l":"Argent 2016 Locale · Problema 107","s":"**Diversion hidrodinamica** PT91. Colegio del Sol. San Migue","f":"ar","c":"Argentina","lv":"Locale","y":"2016"},{"h":"prove/cuadernillo_2016__q73","l":"Argent 2016 Locale · Problema 73","s":"**Transfusion intravenosa** PT57. Instituto Lasalle. Florida","f":"ar","c":"Argentina","lv":"Locale","y":"2016"},{"h":"prove/cuadernillo_2017__q186","l":"Argent 2017 Locale · Problema 186","s":"**Viscosidad por Hagen-Poiseuille** PE25. Escuela Industrial","f":"ar","c":"Argentina","lv":"Locale","y":"2017"},{"h":"prove/cuadernillo_2017__q24","l":"Argent 2017 Locale · Problema 24","s":"PT18. Colegio Juan Humberto Morán Eduardo Castex, La Pampa.","f":"ar","c":"Argentina","lv":"Locale","y":"2017"},{"h":"prove/cuadernillo_2017__q89","l":"Argent 2017 Locale · Problema 89","s":"PT82. Colegio San José de los Hermanos Maristas Escuela Técn","f":"ar","c":"Argentina","lv":"Locale","y":"2017"},{"h":"prove/cuadernillo_2017__q93","l":"Argent 2017 Locale · Problema 93","s":"**Riego en pista de motocross** PT86. EPET N° 4 Juan Agustín","f":"ar","c":"Argentina","lv":"Locale","y":"2017"},{"h":"prove/cuadernillo_2019__q09","l":"Argent 2019 Locale · Problema 09","s":"PT9. Colegio Juan Humberto Morán Eduardo Castex, La Pampa. P","f":"ar","c":"Argentina","lv":"Locale","y":"2019"},{"h":"prove/cuadernillo_2019__q134","l":"Argent 2019 Locale · Problema 134","s":"PT134. Escuela Técnica N° 9 Luis A. Huergo Ciudad Autónoma d","f":"ar","c":"Argentina","lv":"Locale","y":"2019"},{"h":"prove/cuadernillo_2019__q184","l":"Argent 2019 Locale · Problema 184","s":"**Diversion hidrodinamica** PT184. Colegio del Sol - Colegio","f":"ar","c":"Argentina","lv":"Locale","y":"2019"},{"h":"prove/cuadernillo_2019__q223","l":"Argent 2019 Locale · Problema 223","s":"**Hidrodinamica** PE35. Escuela Técnica Alfredo Carlos Passe","f":"ar","c":"Argentina","lv":"Locale","y":"2019"},{"h":"prove/cuadernillo_2019__q242","l":"Argent 2019 Locale · Problema 242","s":"**Determinar la aceleracion de la gravedad aplicando princip","f":"ar","c":"Argentina","lv":"Locale","y":"2019"},{"h":"prove/cuadernillo_2019__q245","l":"Argent 2019 Locale · Problema 245","s":"**Sale chorro (PARTE 2)** PE56. Instituto Privado Rivadavia","f":"ar","c":"Argentina","lv":"Locale","y":"2019"},{"h":"prove/cuadernillo_2019__q42","l":"Argent 2019 Locale · Problema 42","s":"PT42. Instituto Tecnológico del Comahue - San Agustín Intern","f":"ar","c":"Argentina","lv":"Locale","y":"2019"},{"h":"prove/cuadernillo_2020__q09","l":"Argent 2020 Locale · Problema 09","s":"Problema 2 Considere el dispositivo de la figura. El mismo c","f":"ar","c":"Argentina","lv":"Locale","y":"2020"},{"h":"prove/cuadernillo_2020__q113","l":"Argent 2020 Locale · Problema 113","s":"PT103. Escuela Tecnológica Ing. Giúdici Lomas de Zamora, Bue","f":"ar","c":"Argentina","lv":"Locale","y":"2020"},{"h":"prove/cuadernillo_2020__q157","l":"Argent 2020 Locale · Problema 157","s":"**Medicion de volumenes y caudales** PE32. Escuela Superior","f":"ar","c":"Argentina","lv":"Locale","y":"2020"},{"h":"prove/cuadernillo_2020__q160","l":"Argent 2020 Locale · Problema 160","s":"**Analisis de la Ley de Torricelli** PE35. ET N° 9 Ing. Luis","f":"ar","c":"Argentina","lv":"Locale","y":"2020"},{"h":"prove/cuadernillo_2020__q161","l":"Argent 2020 Locale · Problema 161","s":"**Yo mido la gravedad con un chorro de agua** PE36. Colegio","f":"ar","c":"Argentina","lv":"Locale","y":"2020"},{"h":"prove/cuadernillo_2020__q18","l":"Argent 2020 Locale · Problema 18","s":"PT8. Colegio Universitario Central Ciudad de Mendoza. Se dis","f":"ar","c":"Argentina","lv":"Locale","y":"2020"},{"h":"prove/cuadernillo_2020__q30","l":"Argent 2020 Locale · Problema 30","s":"PT20. Escuela Industrial Superior Ciudad de Santa Fe. Existe","f":"ar","c":"Argentina","lv":"Locale","y":"2020"},{"h":"prove/cuadernillo_2020__q87","l":"Argent 2020 Locale · Problema 87","s":"PT77. Escuela Philips Ciudad Autónoma de Buenos Aires. Usted","f":"ar","c":"Argentina","lv":"Locale","y":"2020"},{"h":"prove/esame-secondo-turno-2019-olimpiadi-di-fisica__q12","l":"Svizze 2019 · Problema 12","s":"**Domanda 12** Un fluido omogeneo e incompressibile defluisc","f":"ch","c":"Switzerland","lv":"nazionale","y":"2019"},{"h":"prove/hkpho_2010__q15","l":"HKPhO 2010 · Problema 15","s":"Following MC14, the area of the cross session of the water h","f":"hk","c":"Hong Kong","lv":"Nazionale","y":"2010"},{"h":"prove/hkpho_2012_jl__q11","l":"HKPhO 2012 · Problema 11","s":"**Q1\\* (10 points).** The helicopter has a mass $m$ and main","f":"hk","c":"Hong Kong","lv":"Junior","y":"2012"},{"h":"prove/hkpho_2015__q09","l":"HKPhO 2015 · Problema 09","s":"An electric water pump draws water from a well of depth $10\\","f":"hk","c":"Hong Kong","lv":"Nazionale","y":"2015"},{"h":"prove/librodepruebasoibf1991-2023__q87","l":"iberoa 1991 · Problema 87","s":"**2016 – Teórica P3: Propulsor magnetohidrodinámico (MHD)**","f":"","c":"iberoamericana","lv":"internazionale","y":"1991"},{"h":"prove/obf2007_3fase_1-and-2serie_teorica__q08","l":"OBF 2007 · Problema 08","s":"Num macaco hidráulico os êmbolos apresentam áreas iguais a $","f":"br","c":"Brazil","lv":"qualifica","y":"2007"},{"h":"prove/opho_2023_invitational_theory__q01","l":"OPhO 2023 · Problema 01","s":"**T1: Booster** In this problem, we explore a simplified mod","f":"","c":"International","lv":"Internazionale","y":"2023"},{"h":"prove/plancks_2015__q05","l":"PLANCKS 2015 · Problema 05","s":"**Physics of Oil and Gas Production** (Pavel Levchenko) It i","f":"","c":"International","lv":"Universitario","y":"2015"},{"h":"prove/sjpo_2012__q04","l":"SJPO 2012 · Problema 04","s":"Raindrops fall vertically down to the ground with a speed of","f":"sg","c":"Singapore","lv":"Junior","y":"2012"},{"h":"prove/sjpo_2016__q26","l":"SJPO 2016 · Problema 26","s":"A $0.9\\ \\text{m}$ diameter, water pipe brings water from a r","f":"sg","c":"Singapore","lv":"Junior","y":"2016"},{"h":"prove/sjpo_2022__q22","l":"SJPO 2022 · Problema 22","s":"Water is flowing vertically downward from a tap at a moderat","f":"sg","c":"Singapore","lv":"Junior","y":"2022"},{"h":"prove/sjpo_2023__q17","l":"SJPO 2023 · Problema 17","s":"Water flows from left to right through a horizontal pipe of","f":"sg","c":"Singapore","lv":"Junior","y":"2023"},{"h":"prove/wopho_2012__q09","l":"WoPhO 2012 · Problema 09","s":"**Pouring Water into a Tube** — Deadline July 31, 2012 ### P","f":"","c":"International","lv":"Internazionale","y":"2012"},{"h":"prove/2012_fma__q19","l":"F=ma 2012 · Problema 19","s":"A 1,500 Watt motor is used to pump water a vertical height o","f":"us","c":"United States","lv":"qualifica","y":"2012"}]